Workbook

Sheet Inputs_Assumptions
A1: Parameter | B1: Value | C1: Unit | D1: Data Status | E1: Notes
A2: Selected Course ID | B2: 2 | C2: ID | D2: Illustrative selection | E2: Python Programming Mastery
A3: Selected Course Name | B3: Python Programming Mastery | C3: Text | D3: Frontend fallback mapping | E3: Can be changed
A4: Current Listed Price | B4: 299 | C4: INR | D4: Frontend fallback mapping | E4: Verify against backend
A5: Original Listed Price | B5: 1499 | C5: INR | D5: Frontend fallback mapping | E5: Verify against backend
A6: Baseline Purchases | C6: Count | D6: Not verified | E6: Enter a verified count for a defined period
A7: Website Visitors | C7: Count | D7: Not available | E7: Requires website analytics
A8: Conversion Rate | C8: Percentage | D8: Not available | E8: Calculate only with valid visitor and purchase data
A9: Renewal Rate | C9: Percentage | D9: Not available | E9: Requires subscription history
A10: Higher Price Change | B10: 0.15 | C10: Percentage | D10: Scenario assumption | E10: Editable
A11: Lower Price Change | B11: -0.15 | C11: Percentage | D11: Scenario assumption | E11: Editable
A12: Discount Percentage | B12: 0.2 | C12: Percentage | D12: Scenario assumption | E12: Editable
A13: Annual Plan Discount | B13: 0.2 | C13: Percentage | D13: Illustrative assumption | E13: Verify approved annual-plan terms
A14: Annual Plan Months Charged | B14: 10 | C14: Months | D14: Illustrative assumption | E14: Assumes two months free
A15: Best Case Purchase Change | B15: 0.2 | C15: Percentage | D15: Scenario assumption | E15: Editable
A16: Base Case Purchase Change | B16: 0 | C16: Percentage | D16: Scenario assumption | E16: Editable
A17: Worst Case Purchase Change | B17: -0.2 | C17: Percentage | D17: Scenario assumption | E17: Editable
A18: Price Elasticity | B18: -1 | C18: Factor | D18: Illustrative assumption | E18: Actual customer response unknown
A19: Estimated Variable Cost per Purchase | C19: INR | D19: Not available | E19: Required for profit estimation
A20: Estimated Fixed Costs | C20: INR | D20: Not available | E20: Required for profit estimation
A21: Reporting Period | C21: Period | D21: Not verified | E21: Specify when baseline purchase data is available
A22: Currency | B22: INR | C22: Text | D22: Assumption | E22: Indian rupees

Sheet Course_Price_Reference
A1: Course ID | B1: Course Name | C1: Frontend Listed Price (INR) | D1: Original Listed Price (INR) | E1: Price Difference (INR) | F1: Discount Percentage | G1: Verification Status | H1: Source
A2: 1 | B2: Complete Java Programming | C2: 399 | D2: 1999 | E2: =D2-C2 -> 1600 | F2: =IFERROR(E2/D2,0) -> 0.8004002 | G2: Pending verification | H2: Frontend fallback mapping
A3: 2 | B3: Python Programming Mastery | C3: 299 | D3: 1499 | E3: =D3-C3 -> 1200 | F3: =IFERROR(E3/D3,0) -> 0.80053369 | G3: Pending verification | H3: Frontend fallback mapping
A4: 3 | B4: Flutter Mobile Development | C4: 499 | D4: 2499 | E4: =D4-C4 -> 2000 | F4: =IFERROR(E4/D4,0) -> 0.80032013 | G4: Pending verification | H4: Frontend fallback mapping
A5: 4 | B5: C/C++ Programming Course | C5: 499 | D5: 4999 | E5: =D5-C5 -> 4500 | F5: =IFERROR(E5/D5,0) -> 0.90018004 | G5: Pending verification | H5: Frontend fallback mapping
A6: 5 | B6: C# .NET Development | C6: 1699 | D6: 2299 | E6: =D6-C6 -> 600 | F6: =IFERROR(E6/D6,0) -> 0.26098304 | G6: Pending verification | H6: Frontend fallback mapping
A7: 6 | B7: Data Structures & Algorithms | C7: 2599 | D7: 3499 | E7: =D7-C7 -> 900 | F7: =IFERROR(E7/D7,0) -> 0.25721635 | G7: Pending verification | H7: Frontend fallback mapping
A8: 7 | B8: React Web Development | C8: 2099 | D8: 2799 | E8: =D8-C8 -> 700 | F8: =IFERROR(E8/D8,0) -> 0.25008932 | G8: Pending verification | H8: Frontend fallback mapping

Sheet Pricing_Scenarios
A1: Metric | B1: Current Price | C1: Higher Price | D1: Lower Price | E1: Discounted Price | F1: Annual Plan
A2: Scenario Description | B2: Existing listed price | C2: 15% increase | D2: 15% decrease | E2: 20% discount | F2: Illustrative annual plan
A3: Price per Purchase (INR) | B3: =Inputs_Assumptions!B4 -> 299 | C3: =B3*(1+Inputs_Assumptions!B10) -> 343.85 | D3: =B3*(1+Inputs_Assumptions!B11) -> 254.15 | E3: =B3*(1-Inputs_Assumptions!B12) -> 239.2 | F3: =B3*Inputs_Assumptions!B13 -> 59.8
A4: Annual Plan Months Charged | B4: 12 | C4: 12 | D4: 12 | E4: 12 | F4: =Inputs_Assumptions!B14 -> 10
A5: Total Customer Payment (INR) | B5: =B3*B4 -> 3588 | C5: =C3*C4 -> 4126.2 | D5: =D3*D4 -> 3049.8 | E5: =E3*E4 -> 2870.4 | F5: =F3*F4 -> 598
A6: Baseline Purchases | B6: =IF(Inputs_Assumptions!B6="","",Inputs_Assumptions!B6) | C6: =IF(B6="","",B6) | D6: =IF(B6="","",B6) | E6: =IF(B6="","",B6) | F6: =IF(B6="","",B6)
A7: Assumed Purchase Change % | B7: =Inputs_Assumptions!B16 -> 0 | C7: =Inputs_Assumptions!B15 -> 0.2 | D7: =Inputs_Assumptions!B17 -> -0.2 | E7: =Inputs_Assumptions!B15 -> 0.2 | F7: =Inputs_Assumptions!B15 -> 0.2
A8: Expected Purchases | B8: =IF(B6="","",B6*(1+B7)) | C8: =IF(C6="","",C6*(1+C7)) | D8: =IF(D6="","",D6*(1+D7)) | E8: =IF(E6="","",E6*(1+E7)) | F8: =IF(F6="","",F6*(1+F7))
A9: Simulated Revenue (INR) | B9: =IF(B8="","",B8*B5) | C9: =IF(C8="","",C8*C5) | D9: =IF(D8="","",D8*D5) | E9: =IF(E8="","",E8*E5) | F9: =IF(F8="","",F8*F5)
A10: Revenue Change vs Current | B10: =IF(B9="","",0) | C10: =IF(OR(C9="",B9=0),"",C9/B9-1) | D10: =IF(OR(D9="",B9=0),"",D9/B9-1) | E10: =IF(OR(E9="",B9=0),"",E9/B9-1) | F10: =IF(OR(F9="",B9=0),"",F9/B9-1)
A11: Estimated Variable Costs (INR) | B11: =IF(B8="","",B8*Inputs_Assumptions!B19) | C11: =IF(C8="","",C8*Inputs_Assumptions!B19) | D11: =IF(D8="","",D8*Inputs_Assumptions!B19) | E11: =IF(E8="","",E8*Inputs_Assumptions!B19) | F11: =IF(F8="","",F8*Inputs_Assumptions!B19)
A12: Estimated Fixed Costs (INR) | B12: =IF(B9="","",Inputs_Assumptions!B20) | C12: =IF(C9="","",Inputs_Assumptions!B20) | D12: =IF(D9="","",Inputs_Assumptions!B20) | E12: =IF(E9="","",Inputs_Assumptions!B20) | F12: =IF(F9="","",Inputs_Assumptions!B20)
A13: Estimated Profit (INR) | B13: =IF(B9="","",B9-B11-B12) | C13: =IF(C9="","",C9-C11-C12) | D13: =IF(D9="","",D9-D11-D12) | E13: =IF(E9="","",E9-E11-E12) | F13: =IF(F9="","",F9-F11-F12)
A14: Data Status | B14: Simulation only | C14: Simulation only | D14: Simulation only | E14: Simulation only | F14: Annual terms unverified

Sheet Best_Base_Worst_Case
A1: Metric | B1: Best Case | C1: Base Case | D1: Worst Case
A2: Scenario Description | B2: Optimistic | C2: Purchase count unchanged | D2: Pessimistic
A3: Price Change % | B3: 0 | C3: 0 | D3: 0
A4: Purchase Change % | B4: =Inputs_Assumptions!B15 -> 0.2 | C4: =Inputs_Assumptions!B16 -> 0 | D4: =Inputs_Assumptions!B17 -> -0.2
A5: Current Listed Price (INR) | B5: =Inputs_Assumptions!B4 -> 299 | C5: =Inputs_Assumptions!B4 -> 299 | D5: =Inputs_Assumptions!B4 -> 299
A6: Baseline Purchases | B6: =IF(Inputs_Assumptions!B6="","",Inputs_Assumptions!B6) | C6: =IF(Inputs_Assumptions!B6="","",Inputs_Assumptions!B6) | D6: =IF(Inputs_Assumptions!B6="","",Inputs_Assumptions!B6)
A7: Expected Purchases | B7: =IF(B6="","",B6*(1+B4)) | C7: =IF(C6="","",C6*(1+C4)) | D7: =IF(D6="","",D6*(1+D4))
A8: Simulated Revenue (INR) | B8: =IF(B7="","",B7*B5) | C8: =IF(C7="","",C7*C5) | D8: =IF(D7="","",D7*D5)
A9: Estimated Variable Costs (INR) | B9: =IF(B7="","",B7*Inputs_Assumptions!B19) | C9: =IF(C7="","",C7*Inputs_Assumptions!B19) | D9: =IF(D7="","",D7*Inputs_Assumptions!B19)
A10: Estimated Fixed Costs (INR) | B10: =IF(B7="","",Inputs_Assumptions!B20) | C10: =IF(C7="","",Inputs_Assumptions!B20) | D10: =IF(D7="","",Inputs_Assumptions!B20)
A11: Estimated Profit (INR) | B11: =IF(B8="","",B8-B9-B10) | C11: =IF(C8="","",C8-C9-C10) | D11: =IF(D8="","",D8-D9-D10)
A12: Main Assumption | B12: Purchases increase | C12: Purchases remain stable | D12: Purchases decrease
A13: Data Status | B13: Illustrative | C13: Illustrative | D13: Illustrative

Sheet Revenue_Analysis
A1: Metric | B1: Value | C1: Data Source | D1: Status | E1: Notes
A2: Selected Course | B2: =Inputs_Assumptions!B3 -> Python Programming Mastery | C2: Inputs_Assumptions | D2: Reference | E2: Selected course for the simulation
A3: Frontend Listed Price (INR) | B3: =Inputs_Assumptions!B4 -> 299 | C3: React fallback mapping | D3: Unverified | E3: Confirm backend price
A4: Baseline Purchase Count | B4: =IF(Inputs_Assumptions!B6="","",Inputs_Assumptions!B6) | C4: Verified purchase records | D4: Not entered | E4: Specify reporting period
A5: Simulated Current Revenue (INR) | B5: =IF(B4="","",B3*B4) | C5: Pricing simulation | D5: Conditional | E5: Not actual revenue
A6: Simulated Higher-Price Revenue (INR) | B6: =Pricing_Scenarios!C9 | C6: Pricing simulation | D6: Conditional | E6: Based on scenario assumptions
A7: Simulated Lower-Price Revenue (INR) | B7: =Pricing_Scenarios!D9 | C7: Pricing simulation | D7: Conditional | E7: Based on scenario assumptions
A8: Simulated Discounted Revenue (INR) | B8: =Pricing_Scenarios!E9 | C8: Pricing simulation | D8: Conditional | E8: Based on scenario assumptions
A9: Simulated Annual-Plan Revenue (INR) | B9: =Pricing_Scenarios!F9 | C9: Pricing simulation | D9: Conditional | E9: Annual plan terms unverified
A10: Verified Paid Amount (INR) | C10: Backend payment records | D10: Not available in supplied component | E10: Inspect backend and payment processing
A11: Refund Amount (INR) | C11: Refund records | D11: Not available in supplied component | E11: Verify refund records
A12: Actual Net Revenue (INR) | C12: Verified payments less refunds | D12: Not calculated | E12: Requires validated paid and refund amounts
A13: Renewal Revenue (INR) | C13: Subscription and payment records | D13: Not available in supplied component | E13: Requires renewal data
A14: Variable Costs (INR) | C14: Finance records | D14: Not available | E14: Required for profit
A15: Fixed Costs (INR) | C15: Finance records | D15: Not available | E15: Required for profit
A16: Actual Profit (INR) | C16: Verified revenue and costs | D16: Not calculated | E16: Do not infer from course price

Sheet Sensitivity_Analysis
A1: Price Change % | B1: Elasticity -0.5: Purchase Change % | C1: Elasticity -1.0: Purchase Change % | D1: Elasticity -1.5: Purchase Change %
A2: -0.2 | B2: =(1+A2)^-0.5-1 -> 0.11803399 | C2: =(1+A2)^-1-1 -> 0.25 | D2: =(1+A2)^-1.5-1 -> 0.39754249
A3: -0.15 | B3: =(1+A3)^-0.5-1 -> 0.084652289 | C3: =(1+A3)^-1-1 -> 0.17647059 | D3: =(1+A3)^-1.5-1 -> 0.27606152
A4: -0.1 | B4: =(1+A4)^-0.5-1 -> 0.054092553 | C4: =(1+A4)^-1-1 -> 0.11111111 | D4: =(1+A4)^-1.5-1 -> 0.17121395
A5: -0.05 | B5: =(1+A5)^-0.5-1 -> 0.025978352 | C5: =(1+A5)^-1-1 -> 0.052631579 | D5: =(1+A5)^-1.5-1 -> 0.079977213
A6: 0 | B6: =(1+A6)^-0.5-1 -> 0 | C6: =(1+A6)^-1-1 -> 0 | D6: =(1+A6)^-1.5-1 -> 0
A7: 0.05 | B7: =(1+A7)^-0.5-1 -> -0.024099927 | C7: =(1+A7)^-1-1 -> -0.047619048 | D7: =(1+A7)^-1.5-1 -> -0.070571359
A8: 0.1 | B8: =(1+A8)^-0.5-1 -> -0.046537411 | C8: =(1+A8)^-1-1 -> -0.090909091 | D8: =(1+A8)^-1.5-1 -> -0.13321583
A9: 0.15 | B9: =(1+A9)^-0.5-1 -> -0.067495192 | C9: =(1+A9)^-1-1 -> -0.13043478 | D9: =(1+A9)^-1.5-1 -> -0.18912625
A10: 0.2 | B10: =(1+A10)^-0.5-1 -> -0.087129071 | C10: =(1+A10)^-1-1 -> -0.16666667 | D10: =(1+A10)^-1.5-1 -> -0.23927423

Sheet Scenario_Comparison
A1: Metric | B1: Current Price | C1: Higher Price | D1: Lower Price | E1: Discounted Price | F1: Annual Plan
A2: Price per Purchase (INR) | B2: =Pricing_Scenarios!B3 -> 299 | C2: =Pricing_Scenarios!C3 -> 343.85 | D2: =Pricing_Scenarios!D3 -> 254.15 | E2: =Pricing_Scenarios!E3 -> 239.2 | F2: =Pricing_Scenarios!F3 -> 59.8
A3: Customer Payment (INR) | B3: =Pricing_Scenarios!B5 -> 3588 | C3: =Pricing_Scenarios!C5 -> 4126.2 | D3: =Pricing_Scenarios!D5 -> 3049.8 | E3: =Pricing_Scenarios!E5 -> 2870.4 | F3: =Pricing_Scenarios!F5 -> 598
A4: Baseline Purchases | B4: =Pricing_Scenarios!B6 | C4: =Pricing_Scenarios!C6 | D4: =Pricing_Scenarios!D6 | E4: =Pricing_Scenarios!E6 | F4: =Pricing_Scenarios!F6
A5: Purchase Change % | B5: =Pricing_Scenarios!B7 -> 0 | C5: =Pricing_Scenarios!C7 -> 0.2 | D5: =Pricing_Scenarios!D7 -> -0.2 | E5: =Pricing_Scenarios!E7 -> 0.2 | F5: =Pricing_Scenarios!F7 -> 0.2
A6: Expected Purchases | B6: =Pricing_Scenarios!B8 | C6: =Pricing_Scenarios!C8 | D6: =Pricing_Scenarios!D8 | E6: =Pricing_Scenarios!E8 | F6: =Pricing_Scenarios!F8
A7: Simulated Revenue (INR) | B7: =Pricing_Scenarios!B9 | C7: =Pricing_Scenarios!C9 | D7: =Pricing_Scenarios!D9 | E7: =Pricing_Scenarios!E9 | F7: =Pricing_Scenarios!F9
A8: Revenue Change % | B8: =Pricing_Scenarios!B10 | C8: =Pricing_Scenarios!C10 | D8: =Pricing_Scenarios!D10 | E8: =Pricing_Scenarios!E10 | F8: =Pricing_Scenarios!F10
A9: Estimated Profit (INR) | B9: =Pricing_Scenarios!B13 | C9: =Pricing_Scenarios!C13 | D9: =Pricing_Scenarios!D13 | E9: =Pricing_Scenarios!E13 | F9: =Pricing_Scenarios!F13
A10: Main Advantage | B10: Existing reference | C10: Higher amount per purchase | D10: Lower price may attract buyers | E10: Promotional offer | F10: Potential upfront payment
A11: Main Risk | B11: Price not verified | C11: Demand may decrease | D11: Lower amount per purchase | E11: Reduced amount per purchase | F11: Annual terms unverified
A12: Recommendation | B12: Verify price | C12: Test with measured data | D12: Compare purchase changes | E12: Measure incremental purchases | F12: Confirm plan availability

Sheet Recommendations
A1: Area | B1: Observation | C1: Business Impact | D1: Recommendation | E1: Status
A2: Current Course Pricing | B2: Seven frontend fallback prices are available | C2: Provides initial reference prices | D2: Verify prices against backend course records | E2: Verification required
A3: Higher Pricing | B3: Higher price raises revenue per purchase if demand stays unchanged | C3: Demand may decrease | D3: Test a controlled price change if approved | E3: Scenario only
A4: Lower Pricing | B4: Lower price may attract more purchases | C4: More purchases may not offset the lower price | D4: Compare revenue at different purchase volumes | E4: Scenario only
A5: Discounted Pricing | B5: Discount reduces customer payment | C5: May increase demand but reduce revenue per purchase | D5: Measure incremental purchases and net revenue | E5: Scenario only
A6: Annual Plan | B6: Annual plan terms are not confirmed | C6: Revenue projections may be misleading | D6: Confirm that annual subscriptions are offered | E6: Verification required
A7: Purchase Volume | B7: Baseline purchase count is not verified | C7: Revenue simulations cannot be grounded in actual demand | D7: Validate purchase records and reporting period | E7: Data gap
A8: Payment Verification | B8: Frontend calls purchaseCourse and displays a success alert | C8: Alert alone does not establish gateway payment | D8: Inspect backend purchase and payment verification | E8: Data gap
A9: Conversion Rate | B9: Visitor data is unavailable | C9: Conversion cannot be reliably calculated | D9: Obtain visitor and purchase event data | E9: Data gap
A10: Renewals | B10: Renewal data is unverified | C10: Recurring revenue cannot be reliably estimated | D10: Validate subscription and payment history | E10: Data gap
A11: Profitability | B11: Cost data is unavailable | C11: Revenue does not establish profit | D11: Obtain fixed and variable cost data | E11: Data gap
A12: Final Pricing Decision | B12: Results depend on assumptions | C12: Highest price may not produce the best outcome | D12: Compare verified demand, revenue, costs and retention | E12: After validation

Sheet Source_Audit
A1: Data Item | B1: Source | C1: Status | D1: Action Required
A2: Course ID | B2: React COURSE_MAPPING and backend course API | C2: Frontend fallback IDs identified | D2: Confirm actual backend course records
A3: Course Name | B3: React COURSE_MAPPING and backend course API | C3: Fallback names identified | D3: Confirm against backend records
A4: Current Course Price | B4: React COURSE_MAPPING | C4: Reference only | D4: Verify actual backend price
A5: Original Course Price | B5: React COURSE_MAPPING | C5: Reference only | D5: Verify original price and discount policy
A6: Selected Course | B6: Payment component selectedCourses | C6: Passed through frontend navigation | D6: Confirm selected course and server-side pricing
A7: Displayed Order Total | B7: Payment component state?.total | C7: Displayed frontend amount | D7: Reconcile with backend order total
A8: Purchase API | B8: purchaseCourse(user.id, course.id) | C8: API function called | D8: Inspect course.api.js and backend implementation
A9: Payment Success | B9: Frontend response and alert | C9: Not sufficient to verify payment | D9: Inspect server-side purchase/payment status
A10: Transaction ID | B10: Not shown in supplied component | C10: Not available here | D10: Check backend payment schema
A11: Paid Amount | B11: Not shown in supplied component | C11: Not available here | D11: Check verified payment records
A12: Refund Amount | B12: Not shown in supplied component | C12: Not available here | D12: Check refund records
... A19: Annual Plan Terms | B19: Approved pricing documentation | C19: Not verified | D19: Confirm whether annual plans are offered

Sheet Payment_Data_Audit
A1: Field | B1: Code Reference | C1: Purpose | D1: Current Status | E1: Required Validation
A2: User ID | B2: user.id | C2: Identify the student sent to the purchase API | D2: Passed to API | E2: Verify backend user record
A3: Course ID | B3: course.id | C3: Identify the course being purchased | D3: Passed to API | E3: Verify backend course record
A4: Course Price | B4: course.price | C4: Display individual course price | D4: Displayed in UI | E4: Verify backend price and paid amount
A5: Order Total | B5: state?.total | C5: Display total order amount | D5: Passed through navigation state | E5: Recalculate and verify on backend
A6: Purchase API | B6: purchaseCourse(user.id, course.id) | C6: Submit purchase request | D6: Function called | E6: Inspect course.api.js
A7: API Success | B7: res.success / res.message | C7: Check API response | D7: Frontend condition only | E7: Verify response meaning and server-side status
A8: Payment Gateway | B8: Not shown in supplied component | C8: Process card payment | D8: Not established by this component | E8: Check whether a gateway exists elsewhere
A9: Transaction ID | B9: Not shown in supplied component | C9: Identify transaction | D9: Not available here | E9: Check backend and gateway records
A10: Payment Status | B10: Not shown in supplied component | C10: Identify paid, pending or failed transaction | D10: Not available here | E10: Check backend payment schema
A11: Refund Status | B11: Not shown in supplied component | C11: Identify refunds | D11: Not available here | E11: Check refund records
A12: Renewal Status | B12: Not shown in supplied component | C12: Identify recurring payments | D12: Not available here | E12: Check subscription and renewal APIs
A13: Revenue Calculation | B13: Verified payment records | C13: Calculate actual revenue | D13: Not verified | E13: Use confirmed paid amounts and refunds
