Workbook

Sheet Read Me
A1: CDaX Data Validation & Reconciliation
A2: Pre-commercial validation workbook | Sample/seed review; not a production financial certification.
A4: Item | B4: Details
A5: Purpose | B5: Validate student, course, purchase, enrollment, payment and financial records before commercial launch.
A6: Evidence basis | B6: Previously reviewed CDaX sample/seed workbook and related shared analyses.
A7: Current status | B7: PARTIAL — available sample records can be reviewed; full enrollment-payment and financial reconciliation is pending missing ledgers.
A8: Sample baseline | B8: 3 student accounts; 7 courses; 5 purchase records; 33 modules; 30 videos.
A9: Confirmed anomaly | B9: Purchase record for user 3 dated 1-Jan-2026 predates registration dated 3-Jan-2026 by two days. Root cause is not confirmed.
A10: Important limitation | B10: No separate verified enrollment register, payment transaction ledger, refund ledger or finance summary was available in the reviewed source workbook.
A11: Do not claim | B11: Do not report 100% validation, zero discrepancies, confirmed revenue or completed financial reconciliation.
A12: How to use | B12: Paste full production exports into the input sheets. Preserve source IDs and raw dates. Record each issue in Exception Register.
A13: Financial formula | B13: Net collected = successful gross payments minus completed refunds, using Finance-approved accounting treatment.
A14: Prepared | B14: 30 October 2026

Sheet Reconciliation Summary
A1: Reconciliation Summary
A2: Current evidence-based position. Counts are sample/seed records, not production totals.
A4: Metric | B4: Observed Result | C4: Status | D4: Remarks
A5: Student records reviewed | B5: 3 | C5: Reviewed | D5: Users source table; sample only.
A6: Course records reviewed | B6: 7 | C6: Reviewed | D6: Courses source table.
A7: Purchase records reviewed | B7: 5 | C7: Reviewed | D7: Purchase records do not prove successful payment.
A8: Enrollment records | B8: Unavailable | C8: Blocked | D8: Separate verified enrollment register not supplied.
A9: Payment transactions | B9: Unavailable | C9: Blocked | D9: Payment transaction ledger not supplied.
A10: Refund records | B10: Unavailable | C10: Blocked | D10: Refund ledger not supplied.
A11: Financial summaries | B11: Unavailable | C11: Blocked | D11: Course-wise/monthly finance summary not supplied.
A12: Duplicate student IDs | B12: No duplicate in 3-row sample | C12: Initial check | D12: Repeat on full production export.
A13: Purchase date anomaly | B13: 1 | C13: Confirmed anomaly; cause pending | D13: Purchase date for user 3 predates registration by 2 days.
A14: Financial value of exceptions | B14: Not measurable | C14: Blocked | D14: No verified transaction amounts, statuses or refund values.
A15: Overall reconciliation | B15: PARTIAL | C15: Open | D15: Record checks started; commercial reconciliation pending source data.

Sheet Source Inventory
A1: Source Data Inventory
A2: Available source tables and required missing data.
A4: Source Table | B4: Records Reviewed | C4: Available Fields | D4: Validation Purpose | E4: Missing Information
A5: Users | B5: 3 | C5: id, role, is_active, is_email_verified, is_new_user, created_at, analytics_enabled | D5: Student ID uniqueness and registration checks | E5: Full production student export
A6: Courses | B6: 7 | C6: id, title, category, instructor, instructor_id, enrolled_students, price, discount_price, rating, total_ratings, total_duration_sec, level, sub_category, is_featured, is_popular, is_published | D6: Course master and course references | E6: Approved pricing definitions and authoritative enrollment mapping
A7: Purchases | B7: 5 | C7: id, purchased_on, course_id, user_id | D7: Purchase/user/course reference checks | E7: Payment ID, transaction reference, amount, currency, status, discount and refund
A8: Modules | B8: 33 | C8: id, title, course_id, duration_sec | D8: Course/module relationships | E8: Full production content validation
A9: Videos | B9: 30 | C9: id, title, module_id, duration_sec, display_order, is_preview | D9: Module/video relationships | E9: Playback and QA evidence
A10: Enrollment Register | B10: Unavailable | C10: Not supplied | D10: Enrollment status and payment mapping | E10: Enrollment ID, student ID, course ID, status and date
A11: Payment Ledger | B11: Unavailable | C11: Not supplied | D11: Payment and collection reconciliation | E11: Payment ID, transaction reference, enrollment ID, amount, currency, status and date
A12: Refund Ledger | B12: Unavailable | C12: Not supplied | D12: Refund validation | E12: Refund ID, original payment reference, amount, status and date
A13: Financial Summary | B13: Unavailable | C13: Not supplied | D13: Independent financial total verification | E13: Period, course, gross, discount, refund and net amount

Sheet Validation Rules
A1: Data Validation Rules
A2: Documented, repeatable checks to run against full production exports.
A4: Rule ID | B4: Category | C4: Validation Rule | D4: Validation Method | E4: Expected Result | F4: Severity
A5: DV-01 | B5: Student | C5: Student ID not blank | D5: Check blank IDs | E5: All IDs present | F5: High
A6: DV-02 | B6: Student | C6: Student ID unique | D6: COUNTIF(Student_ID_Range,Student_ID)>1 | E6: No unexplained duplicates | F6: High
A7: DV-03 | B7: Student | C7: Registration date valid | D7: Check blank/invalid timestamps | E7: Valid timestamp | F7: Medium
A8: DV-04 | B8: Course | C8: Course ID not blank | D8: Check blank course IDs | E8: All referenced course IDs present | F8: High
A9: DV-05 | B9: Course | C9: Course ID exists in course master | D9: COUNTIF(Course_Master_ID_Range,Course_ID)>0 | E9: Every reference valid | F9: High
A10: DV-06 | B10: Enrollment | C10: Enrollment ID unique | D10: COUNTIF(Enrollment_ID_Range,Enrollment_ID)>1 | E10: No unexplained duplicate IDs | F10: High
A11: DV-07 | B11: Enrollment | C11: Enrollment status approved | D11: Check approved status list | E11: Only valid statuses | F11: High
A12: DV-08 | B12: Enrollment | C12: Student ID exists in Users | D12: COUNTIF(Users_ID_Range,Student_ID)>0 | E12: Valid student reference | F12: High
A13: DV-09 | B13: Enrollment | C13: Course ID exists in Courses | D13: COUNTIF(Courses_ID_Range,Course_ID)>0 | E13: Valid course reference | F13: High
A14: DV-10 | B14: Payment | C14: Transaction reference not blank | D14: Check blank references | E14: Every payment has reference | F14: High
A15: DV-11 | B15: Payment | C15: Transaction reference unique | D15: COUNTIF(Transaction_Ref_Range,Reference)>1 | E15: No unexplained duplicate transactions | F15: Critical
... A24: DV-20 | B24: Financial | C24: Monthly totals reconcile | D24: Sum transactions by payment month | E24: No unexplained difference | F24: High

Sheet Raw Courses
A1: Raw Courses — Paste Full Export
A2: Paste complete Courses export below; confirm price field definitions.
A4: id | B4: title | C4: category | D4: instructor | E4: instructor_id | F4: enrolled_students | G4: price | H4: discount_price | I4: rating | J4: total_ratings | K4: total_duration_sec | L4: level | M4: sub_category | N4: is_featured | O4: is_popular | P4: is_published

Sheet Raw Purchases
A1: Raw Purchases — Paste Full Export
A2: Paste complete Purchases export below; purchase rows are not payment proof.
A4: id | B4: purchased_on | C4: course_id | D4: user_id

Sheet Raw Enrollments
A1: Raw Enrollments — Paste Full Export
A2: Required input; no separate enrollment register was available.
A4: enrollment_id | B4: student_id | C4: course_id | D4: enrollment_date | E4: enrollment_status

Sheet Raw Payments
A1: Raw Payments — Paste Full Export
A2: Required input; no payment ledger was available.
A4: payment_id | B4: transaction_reference | C4: enrollment_id | D4: student_id | E4: course_id | F4: amount | G4: currency | H4: payment_status | I4: paid_at

Sheet Raw Refunds
A1: Raw Refunds — Paste Full Export
A2: Required input; no refund ledger was available.
A4: refund_id | B4: original_transaction_reference | C4: refund_amount | D4: currency | E4: refund_status | F4: refund_date

Sheet Student Validation
A1: Student Validation
A2: Paste full student export in Raw Users. Formula checks are prepared for up to 500 rows.
A4: Student ID | B4: Role | C4: Registration Date | D4: Account Active | E4: Duplicate ID Check | F4: Date Check | G4: Validation Result | H4: Exception ID | I4: Remarks
A5: =IF(#REF!="","",#REF!) -> #REF! | B5: =IF(A5="","",#REF!) -> #REF! | C5: =IF(A5="","",#REF!) -> #REF! | D5: =IF(A5="","",#REF!) -> #REF! | E5: =IF(A5="","",IF(COUNTIF($A$5:$A$504,A5)>1,"Duplicate","Unique")) -> #REF! | F5: =IF(A5="","",IF(C5="","Missing Date","Date Present")) -> #REF! | G5: =IF(A5="","",IF(OR(E5="Duplicate",F5="Missing Date"),"Review","Pass")) -> #REF!
A6: =IF(#REF!="","",#REF!) -> #REF! | B6: =IF(A6="","",#REF!) -> #REF! | C6: =IF(A6="","",#REF!) -> #REF! | D6: =IF(A6="","",#REF!) -> #REF! | E6: =IF(A6="","",IF(COUNTIF($A$5:$A$504,A6)>1,"Duplicate","Unique")) -> #REF! | F6: =IF(A6="","",IF(C6="","Missing Date","Date Present")) -> #REF! | G6: =IF(A6="","",IF(OR(E6="Duplicate",F6="Missing Date"),"Review","Pass")) -> #REF!
A7: =IF(#REF!="","",#REF!) -> #REF! | B7: =IF(A7="","",#REF!) -> #REF! | C7: =IF(A7="","",#REF!) -> #REF! | D7: =IF(A7="","",#REF!) -> #REF! | E7: =IF(A7="","",IF(COUNTIF($A$5:$A$504,A7)>1,"Duplicate","Unique")) -> #REF! | F7: =IF(A7="","",IF(C7="","Missing Date","Date Present")) -> #REF! | G7: =IF(A7="","",IF(OR(E7="Duplicate",F7="Missing Date"),"Review","Pass")) -> #REF!
A8: =IF(#REF!="","",#REF!) -> #REF! | B8: =IF(A8="","",#REF!) -> #REF! | C8: =IF(A8="","",#REF!) -> #REF! | D8: =IF(A8="","",#REF!) -> #REF! | E8: =IF(A8="","",IF(COUNTIF($A$5:$A$504,A8)>1,"Duplicate","Unique")) -> #REF! | F8: =IF(A8="","",IF(C8="","Missing Date","Date Present")) -> #REF! | G8: =IF(A8="","",IF(OR(E8="Duplicate",F8="Missing Date"),"Review","Pass")) -> #REF!
A9: =IF(#REF!="","",#REF!) -> #REF! | B9: =IF(A9="","",#REF!) -> #REF! | C9: =IF(A9="","",#REF!) -> #REF! | D9: =IF(A9="","",#REF!) -> #REF! | E9: =IF(A9="","",IF(COUNTIF($A$5:$A$504,A9)>1,"Duplicate","Unique")) -> #REF! | F9: =IF(A9="","",IF(C9="","Missing Date","Date Present")) -> #REF! | G9: =IF(A9="","",IF(OR(E9="Duplicate",F9="Missing Date"),"Review","Pass")) -> #REF!
A10: =IF(#REF!="","",#REF!) -> #REF! | B10: =IF(A10="","",#REF!) -> #REF! | C10: =IF(A10="","",#REF!) -> #REF! | D10: =IF(A10="","",#REF!) -> #REF! | E10: =IF(A10="","",IF(COUNTIF($A$5:$A$504,A10)>1,"Duplicate","Unique")) -> #REF! | F10: =IF(A10="","",IF(C10="","Missing Date","Date Present")) -> #REF! | G10: =IF(A10="","",IF(OR(E10="Duplicate",F10="Missing Date"),"Review","Pass")) -> #REF!
A11: =IF(#REF!="","",#REF!) -> #REF! | B11: =IF(A11="","",#REF!) -> #REF! | C11: =IF(A11="","",#REF!) -> #REF! | D11: =IF(A11="","",#REF!) -> #REF! | E11: =IF(A11="","",IF(COUNTIF($A$5:$A$504,A11)>1,"Duplicate","Unique")) -> #REF! | F11: =IF(A11="","",IF(C11="","Missing Date","Date Present")) -> #REF! | G11: =IF(A11="","",IF(OR(E11="Duplicate",F11="Missing Date"),"Review","Pass")) -> #REF!
A12: =IF(#REF!="","",#REF!) -> #REF! | B12: =IF(A12="","",#REF!) -> #REF! | C12: =IF(A12="","",#REF!) -> #REF! | D12: =IF(A12="","",#REF!) -> #REF! | E12: =IF(A12="","",IF(COUNTIF($A$5:$A$504,A12)>1,"Duplicate","Unique")) -> #REF! | F12: =IF(A12="","",IF(C12="","Missing Date","Date Present")) -> #REF! | G12: =IF(A12="","",IF(OR(E12="Duplicate",F12="Missing Date"),"Review","Pass")) -> #REF!
A13: =IF(#REF!="","",#REF!) -> #REF! | B13: =IF(A13="","",#REF!) -> #REF! | C13: =IF(A13="","",#REF!) -> #REF! | D13: =IF(A13="","",#REF!) -> #REF! | E13: =IF(A13="","",IF(COUNTIF($A$5:$A$504,A13)>1,"Duplicate","Unique")) -> #REF! | F13: =IF(A13="","",IF(C13="","Missing Date","Date Present")) -> #REF! | G13: =IF(A13="","",IF(OR(E13="Duplicate",F13="Missing Date"),"Review","Pass")) -> #REF!
A14: =IF(#REF!="","",#REF!) -> #REF! | B14: =IF(A14="","",#REF!) -> #REF! | C14: =IF(A14="","",#REF!) -> #REF! | D14: =IF(A14="","",#REF!) -> #REF! | E14: =IF(A14="","",IF(COUNTIF($A$5:$A$504,A14)>1,"Duplicate","Unique")) -> #REF! | F14: =IF(A14="","",IF(C14="","Missing Date","Date Present")) -> #REF! | G14: =IF(A14="","",IF(OR(E14="Duplicate",F14="Missing Date"),"Review","Pass")) -> #REF!
A15: =IF(#REF!="","",#REF!) -> #REF! | B15: =IF(A15="","",#REF!) -> #REF! | C15: =IF(A15="","",#REF!) -> #REF! | D15: =IF(A15="","",#REF!) -> #REF! | E15: =IF(A15="","",IF(COUNTIF($A$5:$A$504,A15)>1,"Duplicate","Unique")) -> #REF! | F15: =IF(A15="","",IF(C15="","Missing Date","Date Present")) -> #REF! | G15: =IF(A15="","",IF(OR(E15="Duplicate",F15="Missing Date"),"Review","Pass")) -> #REF!
A16: =IF(#REF!="","",#REF!) -> #REF! | B16: =IF(A16="","",#REF!) -> #REF! | C16: =IF(A16="","",#REF!) -> #REF! | D16: =IF(A16="","",#REF!) -> #REF! | E16: =IF(A16="","",IF(COUNTIF($A$5:$A$504,A16)>1,"Duplicate","Unique")) -> #REF! | F16: =IF(A16="","",IF(C16="","Missing Date","Date Present")) -> #REF! | G16: =IF(A16="","",IF(OR(E16="Duplicate",F16="Missing Date"),"Review","Pass")) -> #REF!
... A504: =IF(#REF!="","",#REF!) -> #REF! | B504: =IF(A504="","",#REF!) -> #REF! | C504: =IF(A504="","",#REF!) -> #REF! | D504: =IF(A504="","",#REF!) -> #REF! | E504: =IF(A504="","",IF(COUNTIF($A$5:$A$504,A504)>1,"Duplicate","Unique")) -> #REF! | F504: =IF(A504="","",IF(C504="","Missing Date","Date Present")) -> #REF! | G504: =IF(A504="","",IF(OR(E504="Duplicate",F504="Missing Date"),"Review","Pass")) -> #REF!

Sheet Enrollment Validation
A1: Enrollment Validation
A2: Paste enrollment data into Raw Enrollments; references checked against raw student and course masters.
A4: Enrollment ID | B4: Student ID | C4: Course ID | D4: Enrollment Date | E4: Enrollment Status | F4: Student Exists | G4: Course Exists | H4: Duplicate Enrollment | I4: Validation Result | J4: Exception ID | K4: Remarks
A5: =IF('Raw Enrollments'!A5="","",'Raw Enrollments'!A5) | B5: =IF('Raw Enrollments'!B5="","",'Raw Enrollments'!B5) | C5: =IF('Raw Enrollments'!C5="","",'Raw Enrollments'!C5) | D5: =IF('Raw Enrollments'!D5="","",'Raw Enrollments'!D5) | E5: =IF('Raw Enrollments'!E5="","",'Raw Enrollments'!E5) | F5: =IF(B5="","",IF(COUNTIF(#REF!,B5)>0,"Valid","Invalid Student ID")) | G5: =IF(C5="","",IF(COUNTIF('Raw Courses'!$A:$A,C5)>0,"Valid","Invalid Course ID")) | H5: =IF(A5="","",IF(COUNTIF($A$5:$A$504,A5)>1,"Duplicate","Unique")) | I5: =IF(A5="","",IF(OR(F5="Invalid Student ID",G5="Invalid Course ID",H5="Duplicate",D5="",E5=""),"Review","Pass"))
A6: =IF('Raw Enrollments'!A6="","",'Raw Enrollments'!A6) | B6: =IF('Raw Enrollments'!B6="","",'Raw Enrollments'!B6) | C6: =IF('Raw Enrollments'!C6="","",'Raw Enrollments'!C6) | D6: =IF('Raw Enrollments'!D6="","",'Raw Enrollments'!D6) | E6: =IF('Raw Enrollments'!E6="","",'Raw Enrollments'!E6) | F6: =IF(B6="","",IF(COUNTIF(#REF!,B6)>0,"Valid","Invalid Student ID")) | G6: =IF(C6="","",IF(COUNTIF('Raw Courses'!$A:$A,C6)>0,"Valid","Invalid Course ID")) | H6: =IF(A6="","",IF(COUNTIF($A$5:$A$504,A6)>1,"Duplicate","Unique")) | I6: =IF(A6="","",IF(OR(F6="Invalid Student ID",G6="Invalid Course ID",H6="Duplicate",D6="",E6=""),"Review","Pass"))
A7: =IF('Raw Enrollments'!A7="","",'Raw Enrollments'!A7) | B7: =IF('Raw Enrollments'!B7="","",'Raw Enrollments'!B7) | C7: =IF('Raw Enrollments'!C7="","",'Raw Enrollments'!C7) | D7: =IF('Raw Enrollments'!D7="","",'Raw Enrollments'!D7) | E7: =IF('Raw Enrollments'!E7="","",'Raw Enrollments'!E7) | F7: =IF(B7="","",IF(COUNTIF(#REF!,B7)>0,"Valid","Invalid Student ID")) | G7: =IF(C7="","",IF(COUNTIF('Raw Courses'!$A:$A,C7)>0,"Valid","Invalid Course ID")) | H7: =IF(A7="","",IF(COUNTIF($A$5:$A$504,A7)>1,"Duplicate","Unique")) | I7: =IF(A7="","",IF(OR(F7="Invalid Student ID",G7="Invalid Course ID",H7="Duplicate",D7="",E7=""),"Review","Pass"))
A8: =IF('Raw Enrollments'!A8="","",'Raw Enrollments'!A8) | B8: =IF('Raw Enrollments'!B8="","",'Raw Enrollments'!B8) | C8: =IF('Raw Enrollments'!C8="","",'Raw Enrollments'!C8) | D8: =IF('Raw Enrollments'!D8="","",'Raw Enrollments'!D8) | E8: =IF('Raw Enrollments'!E8="","",'Raw Enrollments'!E8) | F8: =IF(B8="","",IF(COUNTIF(#REF!,B8)>0,"Valid","Invalid Student ID")) | G8: =IF(C8="","",IF(COUNTIF('Raw Courses'!$A:$A,C8)>0,"Valid","Invalid Course ID")) | H8: =IF(A8="","",IF(COUNTIF($A$5:$A$504,A8)>1,"Duplicate","Unique")) | I8: =IF(A8="","",IF(OR(F8="Invalid Student ID",G8="Invalid Course ID",H8="Duplicate",D8="",E8=""),"Review","Pass"))
A9: =IF('Raw Enrollments'!A9="","",'Raw Enrollments'!A9) | B9: =IF('Raw Enrollments'!B9="","",'Raw Enrollments'!B9) | C9: =IF('Raw Enrollments'!C9="","",'Raw Enrollments'!C9) | D9: =IF('Raw Enrollments'!D9="","",'Raw Enrollments'!D9) | E9: =IF('Raw Enrollments'!E9="","",'Raw Enrollments'!E9) | F9: =IF(B9="","",IF(COUNTIF(#REF!,B9)>0,"Valid","Invalid Student ID")) | G9: =IF(C9="","",IF(COUNTIF('Raw Courses'!$A:$A,C9)>0,"Valid","Invalid Course ID")) | H9: =IF(A9="","",IF(COUNTIF($A$5:$A$504,A9)>1,"Duplicate","Unique")) | I9: =IF(A9="","",IF(OR(F9="Invalid Student ID",G9="Invalid Course ID",H9="Duplicate",D9="",E9=""),"Review","Pass"))
A10: =IF('Raw Enrollments'!A10="","",'Raw Enrollments'!A10) | B10: =IF('Raw Enrollments'!B10="","",'Raw Enrollments'!B10) | C10: =IF('Raw Enrollments'!C10="","",'Raw Enrollments'!C10) | D10: =IF('Raw Enrollments'!D10="","",'Raw Enrollments'!D10) | E10: =IF('Raw Enrollments'!E10="","",'Raw Enrollments'!E10) | F10: =IF(B10="","",IF(COUNTIF(#REF!,B10)>0,"Valid","Invalid Student ID")) | G10: =IF(C10="","",IF(COUNTIF('Raw Courses'!$A:$A,C10)>0,"Valid","Invalid Course ID")) | H10: =IF(A10="","",IF(COUNTIF($A$5:$A$504,A10)>1,"Duplicate","Unique")) | I10: =IF(A10="","",IF(OR(F10="Invalid Student ID",G10="Invalid Course ID",H10="Duplicate",D10="",E10=""),"Review","Pass"))
A11: =IF('Raw Enrollments'!A11="","",'Raw Enrollments'!A11) | B11: =IF('Raw Enrollments'!B11="","",'Raw Enrollments'!B11) | C11: =IF('Raw Enrollments'!C11="","",'Raw Enrollments'!C11) | D11: =IF('Raw Enrollments'!D11="","",'Raw Enrollments'!D11) | E11: =IF('Raw Enrollments'!E11="","",'Raw Enrollments'!E11) | F11: =IF(B11="","",IF(COUNTIF(#REF!,B11)>0,"Valid","Invalid Student ID")) | G11: =IF(C11="","",IF(COUNTIF('Raw Courses'!$A:$A,C11)>0,"Valid","Invalid Course ID")) | H11: =IF(A11="","",IF(COUNTIF($A$5:$A$504,A11)>1,"Duplicate","Unique")) | I11: =IF(A11="","",IF(OR(F11="Invalid Student ID",G11="Invalid Course ID",H11="Duplicate",D11="",E11=""),"Review","Pass"))
A12: =IF('Raw Enrollments'!A12="","",'Raw Enrollments'!A12) | B12: =IF('Raw Enrollments'!B12="","",'Raw Enrollments'!B12) | C12: =IF('Raw Enrollments'!C12="","",'Raw Enrollments'!C12) | D12: =IF('Raw Enrollments'!D12="","",'Raw Enrollments'!D12) | E12: =IF('Raw Enrollments'!E12="","",'Raw Enrollments'!E12) | F12: =IF(B12="","",IF(COUNTIF(#REF!,B12)>0,"Valid","Invalid Student ID")) | G12: =IF(C12="","",IF(COUNTIF('Raw Courses'!$A:$A,C12)>0,"Valid","Invalid Course ID")) | H12: =IF(A12="","",IF(COUNTIF($A$5:$A$504,A12)>1,"Duplicate","Unique")) | I12: =IF(A12="","",IF(OR(F12="Invalid Student ID",G12="Invalid Course ID",H12="Duplicate",D12="",E12=""),"Review","Pass"))
A13: =IF('Raw Enrollments'!A13="","",'Raw Enrollments'!A13) | B13: =IF('Raw Enrollments'!B13="","",'Raw Enrollments'!B13) | C13: =IF('Raw Enrollments'!C13="","",'Raw Enrollments'!C13) | D13: =IF('Raw Enrollments'!D13="","",'Raw Enrollments'!D13) | E13: =IF('Raw Enrollments'!E13="","",'Raw Enrollments'!E13) | F13: =IF(B13="","",IF(COUNTIF(#REF!,B13)>0,"Valid","Invalid Student ID")) | G13: =IF(C13="","",IF(COUNTIF('Raw Courses'!$A:$A,C13)>0,"Valid","Invalid Course ID")) | H13: =IF(A13="","",IF(COUNTIF($A$5:$A$504,A13)>1,"Duplicate","Unique")) | I13: =IF(A13="","",IF(OR(F13="Invalid Student ID",G13="Invalid Course ID",H13="Duplicate",D13="",E13=""),"Review","Pass"))
A14: =IF('Raw Enrollments'!A14="","",'Raw Enrollments'!A14) | B14: =IF('Raw Enrollments'!B14="","",'Raw Enrollments'!B14) | C14: =IF('Raw Enrollments'!C14="","",'Raw Enrollments'!C14) | D14: =IF('Raw Enrollments'!D14="","",'Raw Enrollments'!D14) | E14: =IF('Raw Enrollments'!E14="","",'Raw Enrollments'!E14) | F14: =IF(B14="","",IF(COUNTIF(#REF!,B14)>0,"Valid","Invalid Student ID")) | G14: =IF(C14="","",IF(COUNTIF('Raw Courses'!$A:$A,C14)>0,"Valid","Invalid Course ID")) | H14: =IF(A14="","",IF(COUNTIF($A$5:$A$504,A14)>1,"Duplicate","Unique")) | I14: =IF(A14="","",IF(OR(F14="Invalid Student ID",G14="Invalid Course ID",H14="Duplicate",D14="",E14=""),"Review","Pass"))
A15: =IF('Raw Enrollments'!A15="","",'Raw Enrollments'!A15) | B15: =IF('Raw Enrollments'!B15="","",'Raw Enrollments'!B15) | C15: =IF('Raw Enrollments'!C15="","",'Raw Enrollments'!C15) | D15: =IF('Raw Enrollments'!D15="","",'Raw Enrollments'!D15) | E15: =IF('Raw Enrollments'!E15="","",'Raw Enrollments'!E15) | F15: =IF(B15="","",IF(COUNTIF(#REF!,B15)>0,"Valid","Invalid Student ID")) | G15: =IF(C15="","",IF(COUNTIF('Raw Courses'!$A:$A,C15)>0,"Valid","Invalid Course ID")) | H15: =IF(A15="","",IF(COUNTIF($A$5:$A$504,A15)>1,"Duplicate","Unique")) | I15: =IF(A15="","",IF(OR(F15="Invalid Student ID",G15="Invalid Course ID",H15="Duplicate",D15="",E15=""),"Review","Pass"))
A16: =IF('Raw Enrollments'!A16="","",'Raw Enrollments'!A16) | B16: =IF('Raw Enrollments'!B16="","",'Raw Enrollments'!B16) | C16: =IF('Raw Enrollments'!C16="","",'Raw Enrollments'!C16) | D16: =IF('Raw Enrollments'!D16="","",'Raw Enrollments'!D16) | E16: =IF('Raw Enrollments'!E16="","",'Raw Enrollments'!E16) | F16: =IF(B16="","",IF(COUNTIF(#REF!,B16)>0,"Valid","Invalid Student ID")) | G16: =IF(C16="","",IF(COUNTIF('Raw Courses'!$A:$A,C16)>0,"Valid","Invalid Course ID")) | H16: =IF(A16="","",IF(COUNTIF($A$5:$A$504,A16)>1,"Duplicate","Unique")) | I16: =IF(A16="","",IF(OR(F16="Invalid Student ID",G16="Invalid Course ID",H16="Duplicate",D16="",E16=""),"Review","Pass"))
... A504: =IF('Raw Enrollments'!A504="","",'Raw Enrollments'!A504) | B504: =IF('Raw Enrollments'!B504="","",'Raw Enrollments'!B504) | C504: =IF('Raw Enrollments'!C504="","",'Raw Enrollments'!C504) | D504: =IF('Raw Enrollments'!D504="","",'Raw Enrollments'!D504) | E504: =IF('Raw Enrollments'!E504="","",'Raw Enrollments'!E504) | F504: =IF(B504="","",IF(COUNTIF(#REF!,B504)>0,"Valid","Invalid Student ID")) | G504: =IF(C504="","",IF(COUNTIF('Raw Courses'!$A:$A,C504)>0,"Valid","Invalid Course ID")) | H504: =IF(A504="","",IF(COUNTIF($A$5:$A$504,A504)>1,"Duplicate","Unique")) | I504: =IF(A504="","",IF(OR(F504="Invalid Student ID",G504="Invalid Course ID",H504="Duplicate",D504="",E504=""),"Review","Pass"))

Sheet Payment Reconciliation
A1: Enrollment & Payment Reconciliation
A2: Paste raw enrollment and payment exports. Confirm matching keys with Finance/Engineering.
A4: Enrollment ID | B4: Student ID | C4: Course ID | D4: Enrollment Status | E4: Payment ID | F4: Transaction Reference | G4: Payment Amount | H4: Payment Status | I4: Payment Date | J4: Enrollment Match | K4: Payment Reference Check | L4: Reconciliation Result | M4: Exception ID | N4: Remarks
A5: =IF('Raw Enrollments'!A5="","",'Raw Enrollments'!A5) | B5: =IF(A5="","",'Raw Enrollments'!B5) | C5: =IF(A5="","",'Raw Enrollments'!C5) | D5: =IF(A5="","",'Raw Enrollments'!E5) | E5: =IF('Raw Payments'!A5="","",'Raw Payments'!A5) | F5: =IF(E5="","",'Raw Payments'!B5) | G5: =IF(E5="","",'Raw Payments'!F5) | H5: =IF(E5="","",'Raw Payments'!H5) | I5: =IF(E5="","",'Raw Payments'!I5) | J5: =IF(A5="","",IF(COUNTIF('Raw Payments'!$C:$C,A5)>0,"Payment Linked","No Payment")) | K5: =IF(F5="","Missing Reference",IF(COUNTIF('Raw Payments'!$B:$B,F5)>1,"Possible Duplicate","Reference Present")) -> Missing Reference | L5: =IF(A5="","",IF(OR(J5="No Payment",K5="Missing Reference",K5="Possible Duplicate",H5=""),"Review","Check Student/Course/Status"))
A6: =IF('Raw Enrollments'!A6="","",'Raw Enrollments'!A6) | B6: =IF(A6="","",'Raw Enrollments'!B6) | C6: =IF(A6="","",'Raw Enrollments'!C6) | D6: =IF(A6="","",'Raw Enrollments'!E6) | E6: =IF('Raw Payments'!A6="","",'Raw Payments'!A6) | F6: =IF(E6="","",'Raw Payments'!B6) | G6: =IF(E6="","",'Raw Payments'!F6) | H6: =IF(E6="","",'Raw Payments'!H6) | I6: =IF(E6="","",'Raw Payments'!I6) | J6: =IF(A6="","",IF(COUNTIF('Raw Payments'!$C:$C,A6)>0,"Payment Linked","No Payment")) | K6: =IF(F6="","Missing Reference",IF(COUNTIF('Raw Payments'!$B:$B,F6)>1,"Possible Duplicate","Reference Present")) -> Missing Reference | L6: =IF(A6="","",IF(OR(J6="No Payment",K6="Missing Reference",K6="Possible Duplicate",H6=""),"Review","Check Student/Course/Status"))
A7: =IF('Raw Enrollments'!A7="","",'Raw Enrollments'!A7) | B7: =IF(A7="","",'Raw Enrollments'!B7) | C7: =IF(A7="","",'Raw Enrollments'!C7) | D7: =IF(A7="","",'Raw Enrollments'!E7) | E7: =IF('Raw Payments'!A7="","",'Raw Payments'!A7) | F7: =IF(E7="","",'Raw Payments'!B7) | G7: =IF(E7="","",'Raw Payments'!F7) | H7: =IF(E7="","",'Raw Payments'!H7) | I7: =IF(E7="","",'Raw Payments'!I7) | J7: =IF(A7="","",IF(COUNTIF('Raw Payments'!$C:$C,A7)>0,"Payment Linked","No Payment")) | K7: =IF(F7="","Missing Reference",IF(COUNTIF('Raw Payments'!$B:$B,F7)>1,"Possible Duplicate","Reference Present")) -> Missing Reference | L7: =IF(A7="","",IF(OR(J7="No Payment",K7="Missing Reference",K7="Possible Duplicate",H7=""),"Review","Check Student/Course/Status"))
A8: =IF('Raw Enrollments'!A8="","",'Raw Enrollments'!A8) | B8: =IF(A8="","",'Raw Enrollments'!B8) | C8: =IF(A8="","",'Raw Enrollments'!C8) | D8: =IF(A8="","",'Raw Enrollments'!E8) | E8: =IF('Raw Payments'!A8="","",'Raw Payments'!A8) | F8: =IF(E8="","",'Raw Payments'!B8) | G8: =IF(E8="","",'Raw Payments'!F8) | H8: =IF(E8="","",'Raw Payments'!H8) | I8: =IF(E8="","",'Raw Payments'!I8) | J8: =IF(A8="","",IF(COUNTIF('Raw Payments'!$C:$C,A8)>0,"Payment Linked","No Payment")) | K8: =IF(F8="","Missing Reference",IF(COUNTIF('Raw Payments'!$B:$B,F8)>1,"Possible Duplicate","Reference Present")) -> Missing Reference | L8: =IF(A8="","",IF(OR(J8="No Payment",K8="Missing Reference",K8="Possible Duplicate",H8=""),"Review","Check Student/Course/Status"))
A9: =IF('Raw Enrollments'!A9="","",'Raw Enrollments'!A9) | B9: =IF(A9="","",'Raw Enrollments'!B9) | C9: =IF(A9="","",'Raw Enrollments'!C9) | D9: =IF(A9="","",'Raw Enrollments'!E9) | E9: =IF('Raw Payments'!A9="","",'Raw Payments'!A9) | F9: =IF(E9="","",'Raw Payments'!B9) | G9: =IF(E9="","",'Raw Payments'!F9) | H9: =IF(E9="","",'Raw Payments'!H9) | I9: =IF(E9="","",'Raw Payments'!I9) | J9: =IF(A9="","",IF(COUNTIF('Raw Payments'!$C:$C,A9)>0,"Payment Linked","No Payment")) | K9: =IF(F9="","Missing Reference",IF(COUNTIF('Raw Payments'!$B:$B,F9)>1,"Possible Duplicate","Reference Present")) -> Missing Reference | L9: =IF(A9="","",IF(OR(J9="No Payment",K9="Missing Reference",K9="Possible Duplicate",H9=""),"Review","Check Student/Course/Status"))
A10: =IF('Raw Enrollments'!A10="","",'Raw Enrollments'!A10) | B10: =IF(A10="","",'Raw Enrollments'!B10) | C10: =IF(A10="","",'Raw Enrollments'!C10) | D10: =IF(A10="","",'Raw Enrollments'!E10) | E10: =IF('Raw Payments'!A10="","",'Raw Payments'!A10) | F10: =IF(E10="","",'Raw Payments'!B10) | G10: =IF(E10="","",'Raw Payments'!F10) | H10: =IF(E10="","",'Raw Payments'!H10) | I10: =IF(E10="","",'Raw Payments'!I10) | J10: =IF(A10="","",IF(COUNTIF('Raw Payments'!$C:$C,A10)>0,"Payment Linked","No Payment")) | K10: =IF(F10="","Missing Reference",IF(COUNTIF('Raw Payments'!$B:$B,F10)>1,"Possible Duplicate","Reference Present")) -> Missing Reference | L10: =IF(A10="","",IF(OR(J10="No Payment",K10="Missing Reference",K10="Possible Duplicate",H10=""),"Review","Check Student/Course/Status"))
A11: =IF('Raw Enrollments'!A11="","",'Raw Enrollments'!A11) | B11: =IF(A11="","",'Raw Enrollments'!B11) | C11: =IF(A11="","",'Raw Enrollments'!C11) | D11: =IF(A11="","",'Raw Enrollments'!E11) | E11: =IF('Raw Payments'!A11="","",'Raw Payments'!A11) | F11: =IF(E11="","",'Raw Payments'!B11) | G11: =IF(E11="","",'Raw Payments'!F11) | H11: =IF(E11="","",'Raw Payments'!H11) | I11: =IF(E11="","",'Raw Payments'!I11) | J11: =IF(A11="","",IF(COUNTIF('Raw Payments'!$C:$C,A11)>0,"Payment Linked","No Payment")) | K11: =IF(F11="","Missing Reference",IF(COUNTIF('Raw Payments'!$B:$B,F11)>1,"Possible Duplicate","Reference Present")) -> Missing Reference | L11: =IF(A11="","",IF(OR(J11="No Payment",K11="Missing Reference",K11="Possible Duplicate",H11=""),"Review","Check Student/Course/Status"))
A12: =IF('Raw Enrollments'!A12="","",'Raw Enrollments'!A12) | B12: =IF(A12="","",'Raw Enrollments'!B12) | C12: =IF(A12="","",'Raw Enrollments'!C12) | D12: =IF(A12="","",'Raw Enrollments'!E12) | E12: =IF('Raw Payments'!A12="","",'Raw Payments'!A12) | F12: =IF(E12="","",'Raw Payments'!B12) | G12: =IF(E12="","",'Raw Payments'!F12) | H12: =IF(E12="","",'Raw Payments'!H12) | I12: =IF(E12="","",'Raw Payments'!I12) | J12: =IF(A12="","",IF(COUNTIF('Raw Payments'!$C:$C,A12)>0,"Payment Linked","No Payment")) | K12: =IF(F12="","Missing Reference",IF(COUNTIF('Raw Payments'!$B:$B,F12)>1,"Possible Duplicate","Reference Present")) -> Missing Reference | L12: =IF(A12="","",IF(OR(J12="No Payment",K12="Missing Reference",K12="Possible Duplicate",H12=""),"Review","Check Student/Course/Status"))
A13: =IF('Raw Enrollments'!A13="","",'Raw Enrollments'!A13) | B13: =IF(A13="","",'Raw Enrollments'!B13) | C13: =IF(A13="","",'Raw Enrollments'!C13) | D13: =IF(A13="","",'Raw Enrollments'!E13) | E13: =IF('Raw Payments'!A13="","",'Raw Payments'!A13) | F13: =IF(E13="","",'Raw Payments'!B13) | G13: =IF(E13="","",'Raw Payments'!F13) | H13: =IF(E13="","",'Raw Payments'!H13) | I13: =IF(E13="","",'Raw Payments'!I13) | J13: =IF(A13="","",IF(COUNTIF('Raw Payments'!$C:$C,A13)>0,"Payment Linked","No Payment")) | K13: =IF(F13="","Missing Reference",IF(COUNTIF('Raw Payments'!$B:$B,F13)>1,"Possible Duplicate","Reference Present")) -> Missing Reference | L13: =IF(A13="","",IF(OR(J13="No Payment",K13="Missing Reference",K13="Possible Duplicate",H13=""),"Review","Check Student/Course/Status"))
A14: =IF('Raw Enrollments'!A14="","",'Raw Enrollments'!A14) | B14: =IF(A14="","",'Raw Enrollments'!B14) | C14: =IF(A14="","",'Raw Enrollments'!C14) | D14: =IF(A14="","",'Raw Enrollments'!E14) | E14: =IF('Raw Payments'!A14="","",'Raw Payments'!A14) | F14: =IF(E14="","",'Raw Payments'!B14) | G14: =IF(E14="","",'Raw Payments'!F14) | H14: =IF(E14="","",'Raw Payments'!H14) | I14: =IF(E14="","",'Raw Payments'!I14) | J14: =IF(A14="","",IF(COUNTIF('Raw Payments'!$C:$C,A14)>0,"Payment Linked","No Payment")) | K14: =IF(F14="","Missing Reference",IF(COUNTIF('Raw Payments'!$B:$B,F14)>1,"Possible Duplicate","Reference Present")) -> Missing Reference | L14: =IF(A14="","",IF(OR(J14="No Payment",K14="Missing Reference",K14="Possible Duplicate",H14=""),"Review","Check Student/Course/Status"))
A15: =IF('Raw Enrollments'!A15="","",'Raw Enrollments'!A15) | B15: =IF(A15="","",'Raw Enrollments'!B15) | C15: =IF(A15="","",'Raw Enrollments'!C15) | D15: =IF(A15="","",'Raw Enrollments'!E15) | E15: =IF('Raw Payments'!A15="","",'Raw Payments'!A15) | F15: =IF(E15="","",'Raw Payments'!B15) | G15: =IF(E15="","",'Raw Payments'!F15) | H15: =IF(E15="","",'Raw Payments'!H15) | I15: =IF(E15="","",'Raw Payments'!I15) | J15: =IF(A15="","",IF(COUNTIF('Raw Payments'!$C:$C,A15)>0,"Payment Linked","No Payment")) | K15: =IF(F15="","Missing Reference",IF(COUNTIF('Raw Payments'!$B:$B,F15)>1,"Possible Duplicate","Reference Present")) -> Missing Reference | L15: =IF(A15="","",IF(OR(J15="No Payment",K15="Missing Reference",K15="Possible Duplicate",H15=""),"Review","Check Student/Course/Status"))
A16: =IF('Raw Enrollments'!A16="","",'Raw Enrollments'!A16) | B16: =IF(A16="","",'Raw Enrollments'!B16) | C16: =IF(A16="","",'Raw Enrollments'!C16) | D16: =IF(A16="","",'Raw Enrollments'!E16) | E16: =IF('Raw Payments'!A16="","",'Raw Payments'!A16) | F16: =IF(E16="","",'Raw Payments'!B16) | G16: =IF(E16="","",'Raw Payments'!F16) | H16: =IF(E16="","",'Raw Payments'!H16) | I16: =IF(E16="","",'Raw Payments'!I16) | J16: =IF(A16="","",IF(COUNTIF('Raw Payments'!$C:$C,A16)>0,"Payment Linked","No Payment")) | K16: =IF(F16="","Missing Reference",IF(COUNTIF('Raw Payments'!$B:$B,F16)>1,"Possible Duplicate","Reference Present")) -> Missing Reference | L16: =IF(A16="","",IF(OR(J16="No Payment",K16="Missing Reference",K16="Possible Duplicate",H16=""),"Review","Check Student/Course/Status"))
... A504: =IF('Raw Enrollments'!A504="","",'Raw Enrollments'!A504) | B504: =IF(A504="","",'Raw Enrollments'!B504) | C504: =IF(A504="","",'Raw Enrollments'!C504) | D504: =IF(A504="","",'Raw Enrollments'!E504) | E504: =IF('Raw Payments'!A504="","",'Raw Payments'!A504) | F504: =IF(E504="","",'Raw Payments'!B504) | G504: =IF(E504="","",'Raw Payments'!F504) | H504: =IF(E504="","",'Raw Payments'!H504) | I504: =IF(E504="","",'Raw Payments'!I504) | J504: =IF(A504="","",IF(COUNTIF('Raw Payments'!$C:$C,A504)>0,"Payment Linked","No Payment")) | K504: =IF(F504="","Missing Reference",IF(COUNTIF('Raw Payments'!$B:$B,F504)>1,"Possible Duplicate","Reference Present")) -> Missing Reference | L504: =IF(A504="","",IF(OR(J504="No Payment",K504="Missing Reference",K504="Possible Duplicate",H504=""),"Review","Check Student/Course/Status"))

Sheet Financial Reconciliation
A1: Financial Reconciliation
A2: Enter verified transaction totals and finance-reported totals. Do not use catalogue price as collected revenue.
A4: Reporting Period | B4: Course ID | C4: Transaction Count | D4: Gross Successful Payments | E4: Discount Amount | F4: Completed Refund Amount | G4: Net Calculated Amount | H4: Reported Net Amount | I4: Difference | J4: Status | K4: Remarks
G5: =IF(OR(D5="",F5=""),"",D5-F5) | I5: =IF(OR(G5="",H5=""),"",G5-H5) | J5: =IF(H5="","Reported Amount Missing",IF(ABS(I5)<0.01,"Matched","Difference Found")) -> Reported Amount Missing
G6: =IF(OR(D6="",F6=""),"",D6-F6) | I6: =IF(OR(G6="",H6=""),"",G6-H6) | J6: =IF(H6="","Reported Amount Missing",IF(ABS(I6)<0.01,"Matched","Difference Found")) -> Reported Amount Missing
G7: =IF(OR(D7="",F7=""),"",D7-F7) | I7: =IF(OR(G7="",H7=""),"",G7-H7) | J7: =IF(H7="","Reported Amount Missing",IF(ABS(I7)<0.01,"Matched","Difference Found")) -> Reported Amount Missing
G8: =IF(OR(D8="",F8=""),"",D8-F8) | I8: =IF(OR(G8="",H8=""),"",G8-H8) | J8: =IF(H8="","Reported Amount Missing",IF(ABS(I8)<0.01,"Matched","Difference Found")) -> Reported Amount Missing
G9: =IF(OR(D9="",F9=""),"",D9-F9) | I9: =IF(OR(G9="",H9=""),"",G9-H9) | J9: =IF(H9="","Reported Amount Missing",IF(ABS(I9)<0.01,"Matched","Difference Found")) -> Reported Amount Missing
G10: =IF(OR(D10="",F10=""),"",D10-F10) | I10: =IF(OR(G10="",H10=""),"",G10-H10) | J10: =IF(H10="","Reported Amount Missing",IF(ABS(I10)<0.01,"Matched","Difference Found")) -> Reported Amount Missing
G11: =IF(OR(D11="",F11=""),"",D11-F11) | I11: =IF(OR(G11="",H11=""),"",G11-H11) | J11: =IF(H11="","Reported Amount Missing",IF(ABS(I11)<0.01,"Matched","Difference Found")) -> Reported Amount Missing
G12: =IF(OR(D12="",F12=""),"",D12-F12) | I12: =IF(OR(G12="",H12=""),"",G12-H12) | J12: =IF(H12="","Reported Amount Missing",IF(ABS(I12)<0.01,"Matched","Difference Found")) -> Reported Amount Missing
G13: =IF(OR(D13="",F13=""),"",D13-F13) | I13: =IF(OR(G13="",H13=""),"",G13-H13) | J13: =IF(H13="","Reported Amount Missing",IF(ABS(I13)<0.01,"Matched","Difference Found")) -> Reported Amount Missing
G14: =IF(OR(D14="",F14=""),"",D14-F14) | I14: =IF(OR(G14="",H14=""),"",G14-H14) | J14: =IF(H14="","Reported Amount Missing",IF(ABS(I14)<0.01,"Matched","Difference Found")) -> Reported Amount Missing
G15: =IF(OR(D15="",F15=""),"",D15-F15) | I15: =IF(OR(G15="",H15=""),"",G15-H15) | J15: =IF(H15="","Reported Amount Missing",IF(ABS(I15)<0.01,"Matched","Difference Found")) -> Reported Amount Missing
G16: =IF(OR(D16="",F16=""),"",D16-F16) | I16: =IF(OR(G16="",H16=""),"",G16-H16) | J16: =IF(H16="","Reported Amount Missing",IF(ABS(I16)<0.01,"Matched","Difference Found")) -> Reported Amount Missing
... G204: =IF(OR(D204="",F204=""),"",D204-F204) | I204: =IF(OR(G204="",H204=""),"",G204-H204) | J204: =IF(H204="","Reported Amount Missing",IF(ABS(I204)<0.01,"Matched","Difference Found")) -> Reported Amount Missing

Sheet Exception Register
A1: Exception Tracking Register
A2: Initial evidence gaps and one identified date anomaly. These are not all confirmed financial errors.
A4: Exception ID | B4: Date Identified | C4: Category | D4: Record ID | E4: Student ID | F4: Course ID | G4: Transaction Reference | H4: Discrepancy Description | I4: Exception Type | J4: Severity | K4: Financial Impact | L4: Root Cause | M4: Status | N4: Recommended Action | O4: Responsible Team | P4: Resolution Date
A5: EX-001 | C5: Financial | H5: Payment amount and status unavailable in reviewed source. | I5: Data Gap | J5: High | K5: Not Measurable | L5: Pending payment export | M5: Open | N5: Obtain payment ledger and reconcile with purchase records. | O5: Finance / Engineering
A6: EX-002 | C6: Enrollment | H6: Separate enrollment register unavailable. | I6: Data Gap | J6: High | K6: Not Measurable | L6: Pending enrollment export | M6: Open | N6: Obtain enrollment export with IDs, status and date. | O6: Product / Engineering
A7: EX-003 | C7: Data Quality | D7: Purchase row 1 | E7: 3 | H7: Purchase dated 1-Jan-2026 predates registration dated 3-Jan-2026 by two days. | I7: Confirmed Date-Sequence Anomaly | J7: High | K7: Not Measurable | L7: Cause not confirmed; investigate timezone, source clock and import history. | M7: Open | N7: Investigate timestamps and import history; preserve raw dates. | O7: Data / Backend
A8: EX-004 | C8: Commercial | H8: Course price and discount_price field meanings require confirmation. | I8: Needs Investigation | J8: Medium | K8: Not Measurable | L8: Backend/product definition not confirmed | M8: Open | N8: Confirm canonical price definitions. | O8: Product / Finance
A9: EX-005 | C9: Refunds | I9: Refund transactions and amounts unavailable. | J9: Data Gap | K9: High | L9: Not Measurable | M9: Pending refund export | N9: Open | O9: Obtain refund ledger linked to original payment references. | P9: Finance

Sheet Corrective Action Plan
A1: Corrective Action Plan
A2: Controls required to close identified gaps and prevent recurrence.
A4: Action ID | B4: Issue | C4: Corrective Action | D4: Prevention Control | E4: Responsible Function | F4: Priority | G4: Completion Evidence | H4: Status
A5: CA-01 | B5: Missing enrollment register | C5: Obtain complete enrollment export with enrollment ID, student ID, course ID, date and status | D5: Make key fields mandatory in enrollment creation | E5: Product / Engineering | F5: High | G5: Validated enrollment export | H5: Open
A6: CA-02 | B6: Missing payment ledger | C6: Obtain payment gateway transaction export | D6: Store unique transaction reference for each payment attempt | E6: Finance / Engineering | F6: Critical | G6: Payment transaction ledger | H6: Open
A7: CA-03 | B7: Missing refund information | C7: Obtain refund records linked to original transactions | D7: Require original payment reference for every refund | E7: Finance | F7: Critical | G7: Refund reconciliation report | H7: Open
A8: CA-04 | B8: Student/course reference issues | C8: Validate IDs against master tables | D8: Apply foreign-key and referential-integrity checks | E8: Engineering | F8: High | G8: Validation results | H8: Open
A9: CA-05 | B9: Purchase date anomaly | C9: Check timezone, source clock and import process | D9: Use consistent timestamp and timezone rules | E9: Data / Backend | F9: High | G9: Root-cause confirmation | H9: Open
A10: CA-06 | B10: Price field ambiguity | C10: Confirm price and discount_price definitions | D10: Approve one canonical pricing definition | E10: Product / Finance | F10: Medium | G10: Approved field definition | H10: Open
A11: CA-07 | B11: Financial reporting differences | C11: Recalculate totals from transaction-level records | D11: Automate course-wise and monthly reconciliation | E11: Finance | F11: High | G11: Signed reconciliation report | H11: Open
